wui_python_additions/__init__.py
wui_python_additions/configuration.py
wui_python_additions/process_watcher.py
wui_python_additions-0.1.2.dist-info/METADATA
wui_python_additions-0.1.2.dist-info/WHEEL
wui_python_additions-0.1.2.dist-info/top_level.txt
wui_python_additions-0.1.2.dist-info/RECORD
