Metadata-Version: 2.1
Name: wui-python-additions
Version: 0.1.2
Summary: TODO
Author-email: Igor Toropov <it.cups.54@gmail.com>
License: MIT
Classifier: Programming Language :: Python :: 3
Classifier: License :: OSI Approved :: MIT License
Classifier: Operating System :: OS Independent
Requires-Python: >=3.9
Requires-Dist: autopep8 ==2.0.2
